proptools.py
proptools-0.2.dist-info/DESCRIPTION.rst
proptools-0.2.dist-info/METADATA
proptools-0.2.dist-info/RECORD
proptools-0.2.dist-info/WHEEL
proptools-0.2.dist-info/metadata.json
proptools-0.2.dist-info/top_level.txt
