Metadata-Version: 2.0
Name: proptools
Version: 0.2
Summary: Property types: LazyProperty, TypedProperty, SetOnceProperty
Home-page: https://github.org/nejucomo/proptools
Author: Nathan Wilcox
Author-email: nejucomo@gmail.com
License: MIT (see LICENSE.txt)
Platform: UNKNOWN
